PyAstronomy_ext/__init__.py
PyAstronomy_ext/__pycache__/__init__.cpython-314.pyc
PyAstronomy_ext/forTrans/__init__.py
PyAstronomy_ext/forTrans/occultnl.cpython-38-x86_64-linux-gnu.so
PyAstronomy_ext/forTrans/occultquad.cpython-38-x86_64-linux-gnu.so
pyastronomy_ext.libs/libgfortran-83c28eba.so.5.0.0
pyastronomy_ext.libs/libmvec-2-583a17db.28.so
pyastronomy_ext.libs/libquadmath-2284e583.so.0.0.0
pyastronomy_ext-2.dist-info/METADATA
pyastronomy_ext-2.dist-info/WHEEL
pyastronomy_ext-2.dist-info/RECORD
