Metadata-Version: 2.1
Name: PyAstronomy-ext
Version: 2
Summary: Optional extension for PyAstronomy.
Author-Email: PyA group <stefan.czesla@hs.uni-hamburg.de>
License: MIT
Requires-Python: >=3.8
Requires-Dist: numpy
Requires-Dist: six
